champ/PartitionEnsemble.py
champ/__init__.py
champ/_version.py
champ/champ_functions.py
champ/genlouvain.py
champ/leiden_ext.py
champ/louvain_ext.py
champ/louvain_ml_extension.py
champ/manual_champ.py
champ/parameter_estimation.py
champ/plot_domains.py
champ/test_champ.py
champ/test_directed_louvain.py
champ/test_gamma_estimation.py
champ/test_louvain_ext.py
champ-2.1.1.dist-info/LICENSE
champ-2.1.1.dist-info/METADATA
champ-2.1.1.dist-info/WHEEL
champ-2.1.1.dist-info/dependency_links.txt
champ-2.1.1.dist-info/top_level.txt
champ-2.1.1.dist-info/RECORD
