Metadata-Version: 2.1
Name: champ
Version: 2.1.1
Summary: Modularity based networks partition selection tool
Home-page: http://github.com/wweir827/champ
Author: William H. Weir
Author-email: wweir@med.unc.edu
License: GPLv3+
Platform: UNKNOWN
Classifier: Programming Language :: Python :: 2.7
Classifier: Programming Language :: Python :: 3.6
Classifier: License :: OSI Approved :: GNU General Public License v3 or later (GPLv3+)
Classifier: Topic :: Scientific/Engineering :: Information Analysis
Provides: champ
Requires-Dist: matplotlib
Requires-Dist: future
Requires-Dist: numpy (>1.13)
Requires-Dist: h5py
Requires-Dist: scipy (>=0.19)
Requires-Dist: scikit-learn
Requires-Dist: louvain
Requires-Dist: leidenalg
Requires-Dist: python-igraph
Requires-Dist: seaborn
Requires-Dist: tqdm
